[
  {
    "id": "1",
    "title": "Citigroup lowers Bitcoin and Ethereum forecasts as US crypto regulation stalls",
    "source": "Reuters",
    "published": "2026-03-17T09:00:00.000Z",
    "coins": ["BTC", "ETH"]
  },
  {
    "id": "2",
    "title": "Bitcoin rises during Federal Reserve meeting as investors react to inflation and geopolitical tensions",
    "source": "Barron's",
    "published": "2026-03-17T08:00:00.000Z",
    "coins": ["BTC", "ETH", "XRP"]
  },
  {
    "id": "3",
    "title": "Bitcoin rebounds above $70,000 as market volatility eases and investor confidence returns",
    "source": "CoinDesk",
    "published": "2026-03-16T18:00:00.000Z",
    "coins": ["BTC"]
  },
  {
    "id": "4",
    "title": "Crypto funds record over $600 million in weekly inflows led by Bitcoin and Ethereum",
    "source": "Seeking Alpha",
    "published": "2026-03-15T14:00:00.000Z",
    "coins": ["BTC", "ETH", "SOL"]
  },
  {
    "id": "5",
    "title": "Bitcoin climbs past $73,000 boosting crypto-related stocks after recent market turbulence",
    "source": "Wall Street Journal",
    "published": "2026-03-14T12:00:00.000Z",
    "coins": ["BTC"]
  },
  {
    "id": "6",
    "title": "Bitcoin rebounds toward $72K as US Treasury comments ease inflation concerns",
    "source": "Economic Times",
    "published": "2026-03-13T10:00:00.000Z",
    "coins": ["BTC"]
  },
  {
    "id": "7",
    "title": "Charles Schwab prepares to launch direct Bitcoin and Ethereum trading for clients",
    "source": "Barron's",
    "published": "2026-03-12T16:00:00.000Z",
    "coins": ["BTC", "ETH"]
  },
  {
    "id": "8",
    "title": "Bitcoin approaches $70,000 as weaker dollar and easing geopolitical tensions improve sentiment",
    "source": "Economic Times",
    "published": "2026-03-11T09:00:00.000Z",
    "coins": ["BTC"]
  }
]
